MANIFEST.in
README.md
setup.cfg
setup.py
nose_cprof.egg-info/PKG-INFO
nose_cprof.egg-info/SOURCES.txt
nose_cprof.egg-info/dependency_links.txt
nose_cprof.egg-info/entry_points.txt
nose_cprof.egg-info/not-zip-safe
nose_cprof.egg-info/requires.txt
nose_cprof.egg-info/top_level.txt
nose_cprofile/__init__.py
nose_cprofile/__init__.pyc
nose_cprofile/nose_cprofile.py
nose_cprofile/nose_cprofile.pyc