Metadata-Version: 1.1
Name: nose-cprof
Version: 0.2.1
Summary: A python nose plugin to profile using cProfile rather than the default Hotshot profiler.
Home-page: https://github.com/msherry/nose-cprof
Author: Marc Sherry
Author-email: msherry@gmail.com
License: UNKNOWN
Platform: UNKNOWN
Classifier: Intended Audience :: Developers
Classifier: License :: OSI Approved :: BSD License
Classifier: Programming Language :: Python
Classifier: Topic :: Software Development :: Libraries :: Python Modules
